[{"date":"Thu, 29 Oct 2015 12:52:51 GMT","sloc":6,"lloc":5,"functions":1,"deliveredBugs":0.040371202821288026,"maintainability":75.64300331094367,"lintErrors":[],"difficulty":3.272727272727273},{"date":"Thu, 29 Oct 2015 13:01:26 GMT","sloc":6,"lloc":5,"functions":1,"deliveredBugs":0.040371202821288026,"maintainability":75.64300331094367,"lintErrors":[],"difficulty":3.272727272727273},{"date":"Thu, 29 Oct 2015 13:01:39 GMT","sloc":6,"lloc":5,"functions":1,"deliveredBugs":0.040371202821288026,"maintainability":75.64300331094367,"lintErrors":[],"difficulty":3.272727272727273},{"date":"Thu, 29 Oct 2015 13:03:23 GMT","sloc":6,"lloc":5,"functions":1,"deliveredBugs":0.040371202821288026,"maintainability":75.64300331094367,"lintErrors":[],"difficulty":3.272727272727273},{"date":"Thu, 29 Oct 2015 13:05:25 GMT","sloc":6,"lloc":5,"functions":1,"deliveredBugs":0.040371202821288026,"maintainability":75.64300331094367,"lintErrors":[],"difficulty":3.272727272727273},{"date":"Thu, 29 Oct 2015 13:08:46 GMT","sloc":6,"lloc":5,"functions":1,"deliveredBugs":0.040371202821288026,"maintainability":75.64300331094367,"lintErrors":[],"difficulty":3.272727272727273},{"date":"Thu, 29 Oct 2015 13:22:58 GMT","sloc":6,"lloc":5,"functions":1,"deliveredBugs":0.040371202821288026,"maintainability":75.64300331094367,"lintErrors":[],"difficulty":3.272727272727273},{"date":"Thu, 29 Oct 2015 13:25:16 GMT","sloc":6,"lloc":5,"functions":1,"deliveredBugs":0.040371202821288026,"maintainability":75.64300331094367,"lintErrors":[],"difficulty":3.272727272727273},{"date":"Thu, 29 Oct 2015 13:25:45 GMT","sloc":6,"lloc":5,"functions":1,"deliveredBugs":0.040371202821288026,"maintainability":75.64300331094367,"lintErrors":[],"difficulty":3.272727272727273},{"date":"Thu, 29 Oct 2015 13:26:12 GMT","sloc":6,"lloc":5,"functions":1,"deliveredBugs":0.040371202821288026,"maintainability":75.64300331094367,"lintErrors":[],"difficulty":3.272727272727273},{"date":"Thu, 29 Oct 2015 13:29:17 GMT","sloc":6,"lloc":5,"functions":1,"deliveredBugs":0.040371202821288026,"maintainability":75.64300331094367,"lintErrors":[],"difficulty":3.272727272727273},{"date":"Thu, 29 Oct 2015 13:29:25 GMT","sloc":6,"lloc":5,"functions":1,"deliveredBugs":0.040371202821288026,"maintainability":75.64300331094367,"lintErrors":[],"difficulty":3.272727272727273},{"date":"Thu, 29 Oct 2015 13:42:28 GMT","sloc":6,"lloc":5,"functions":1,"deliveredBugs":0.040371202821288026,"maintainability":75.64300331094367,"lintErrors":[],"difficulty":3.272727272727273},{"date":"Thu, 29 Oct 2015 13:44:04 GMT","sloc":6,"lloc":5,"functions":1,"deliveredBugs":0.040371202821288026,"maintainability":75.64300331094367,"lintErrors":[],"difficulty":3.272727272727273}]