[{"date":"Thu, 29 Sep 2016 13:55:03 GMT","sloc":43,"lloc":25,"functions":4,"deliveredBugs":0.2909951055807412,"maintainability":122.69596876392623,"lintErrors":[],"difficulty":9.222222222222223},{"date":"Thu, 29 Sep 2016 14:24:45 GMT","sloc":43,"lloc":25,"functions":4,"deliveredBugs":0.2909951055807412,"maintainability":122.69596876392623,"lintErrors":[],"difficulty":9.222222222222223},{"date":"Mon, 21 Nov 2016 11:48:51 GMT","sloc":43,"lloc":25,"functions":4,"deliveredBugs":0.2909951055807412,"maintainability":122.69596876392623,"lintErrors":[],"difficulty":9.222222222222223},{"date":"Mon, 21 Nov 2016 11:49:07 GMT","sloc":43,"lloc":25,"functions":4,"deliveredBugs":0.2909951055807412,"maintainability":122.69596876392623,"lintErrors":[],"difficulty":9.222222222222223}]